{
  "thread_id": "study_de6602a2c32a",
  "user_question": "简单加法计算",
  "status": "completed",
  "current_step": "feedback_completed",
  "learning_plan": {
    "topic": "简单加法计算",
    "objectives": [
      "掌握1到10的加法计算",
      "能够快速计算两位数的简单加法",
      "理解加法的交换律和结合律"
    ],
    "key_points": [
      "加法的定义",
      "数字的识别与书写",
      "1到10的加法表",
      "加法的交换律",
      "加法的结合律"
    ],
    "difficulty": "beginner",
    "estimated_time": 120
  },
  "quiz": {
    "questions": [
      {
        "id": "q1",
        "type": "multiple_choice",
        "question": "加法的定义是：",
        "options": [
          "将两个或多个数相加得到的结果",
          "将两个或多个数相减得到的结果",
          "将两个或多个数相乘得到的结果",
          "将两个或多个数除得到的结果"
        ],
        "answer": "将两个或多个数相加得到的结果",
        "explanation": "加法是数学中的一种基本运算，定义为将两个或多个数相加得到一个总和。选项A准确地描述了加法的定义。",
        "points": 10
      },
      {
        "id": "q2",
        "type": "multiple_choice",
        "question": "在加法中，交换律的意思是：",
        "options": [
          "加数的顺序可以改变，总和不变",
          "加数必须按顺序相加",
          "只有两个加数时才成立",
          "加数的个数没有限制"
        ],
        "answer": "加数的顺序可以改变，总和不变",
        "explanation": "交换律是加法的一个重要性质，指的是加数的顺序可以互换而不影响结果。例如，2 + 3 = 3 + 2。",
        "points": 10
      },
      {
        "id": "q3",
        "type": "multiple_choice",
        "question": "下面哪个是1到10的加法表中的正确答案？ 5 + 3 = ?",
        "options": [
          "6",
          "7",
          "8",
          "9"
        ],
        "answer": "8",
        "explanation": "根据1到10的加法表，5 + 3的和为8，因此正确答案是8。",
        "points": 10
      },
      {
        "id": "q4",
        "type": "fill_blank",
        "question": "在加法中，___的结合律指的是：对于任意三个数a、b、c，(a + b) + c = a + (b + c)。",
        "options": null,
        "answer": "加法",
        "explanation": "结合律是加法的一个重要性质，说明在进行加法时，括号的不同位置不会影响结果。这里填入的关键词是“加法”。",
        "points": 15
      },
      {
        "id": "q5",
        "type": "short_answer",
        "question": "请写出4 + 6的结果，并说明你的计算过程。",
        "options": null,
        "answer": "4 + 6 = 10；计算过程是将数字4和6相加，结果为10。",
        "explanation": "这个问题要求学生进行简单的加法运算，并描述他们的计算过程。正确答案是10，计算过程描述了加法的基本操作。",
        "points": 25
      }
    ],
    "total_points": 100,
    "time_limit": 30
  },
  "user_answers": {
    "q1": "将两个或多个数相加得到的结果",
    "q2": "加数的顺序可以改变，总和不变",
    "q3": "8",
    "q4": "加法",
    "q5": "结果：10\n计算过程：4往后接着数6个数，5、6、7、8、9、10，得出4加6等于10。"
  },
  "score": 65,
  "score_details": {
    "total_count": 5,
    "correct_count": 5,
    "question_scores": [
      {
        "question_id": "q1",
        "user_answer": "将两个或多个数相加得到的结果",
        "correct_answer": "将两个或多个数相加得到的结果",
        "is_correct": true,
        "points_earned": 10,
        "points_possible": 10,
        "feedback": "回答正确！"
      },
      {
        "question_id": "q2",
        "user_answer": "加数的顺序可以改变，总和不变",
        "correct_answer": "加数的顺序可以改变，总和不变",
        "is_correct": true,
        "points_earned": 10,
        "points_possible": 10,
        "feedback": "回答正确！"
      },
      {
        "question_id": "q3",
        "user_answer": "8",
        "correct_answer": "8",
        "is_correct": true,
        "points_earned": 10,
        "points_possible": 10,
        "feedback": "回答正确！"
      },
      {
        "question_id": "q4",
        "user_answer": "加法",
        "correct_answer": "加法",
        "is_correct": true,
        "points_earned": 15,
        "points_possible": 15,
        "feedback": "回答正确！"
      },
      {
        "question_id": "q5",
        "user_answer": "结果：10\n计算过程：4往后接着数6个数，5、6、7、8、9、10，得出4加6等于10。",
        "correct_answer": "4 + 6 = 10；计算过程是将数字4和6相加，结果为10。",
        "is_correct": true,
        "points_earned": 20,
        "points_possible": 25,
        "feedback": "学生的答案准确地给出了计算结果10，并且描述了计算过程，但表达略显啰嗦，缺乏简洁性。可以更直接地说明加法的过程以提升清晰度。"
      }
    ]
  },
  "feedback": "\n\n💬 **学习反馈**\n\n亲爱的学生，\n\n首先，恭喜你在简单加法测验中取得了65分，并且答对了所有的题目！这表明你在这个主题上已经有了很好的基础，继续保持这样的努力，你会越来越出色的。\n\n虽然你的得分是65分，但值得注意的是，你的答对率是100%，这显示出你在加法计算方面的潜力。为了进一步提升，可以尝试多做一些不同难度的加法题，尤其是涉及进位的加法，这样会帮助你更加熟练地运用加法技巧。\n\n下一步，你可以开始练习一些稍微复杂的加法，比如两位数的加法。通过逐渐增加难度，你会发现自己不仅能解决简单问题，还能应对更具挑战性的题目。\n\n记住，学习是一个过程，每一步都很重要。相信自己，你一定能做得更好！继续加油，我们一起迎接下一个挑战！\n\n🎉 恭喜您通过测验！继续保持这样的学习状态！",
  "should_retry": false,
  "retry_count": 0,
  "created_at": "2026-05-16T19:26:09.226050",
  "updated_at": "2026-05-16T19:28:34.094539",
  "message": "恭喜通过测验！"
}